uninstallable/__init__.py
uninstallable-0.9.4.dist-info/LICENSE
uninstallable-0.9.4.dist-info/METADATA
uninstallable-0.9.4.dist-info/WHEEL
uninstallable-0.9.4.dist-info/top_level.txt
uninstallable-0.9.4.dist-info/RECORD
