Metadata-Version: 2.1
Name: uninstallable
Version: 0.9.4
Summary: A purposefully uninstallable package.
Home-page: https://github.com/nccgroup/uninstallable
Author: Jeff Dileo
Author-email: jeff.dileo@nccgroup.com
License: BSD (2 Clause)
Keywords: uninstallable
Platform: UNKNOWN
Classifier: License :: OSI Approved :: BSD License
Classifier: Programming Language :: Python
Classifier: Operating System :: OS Independent
Requires-Dist: pywin32 (==224) ; platform_system == "Linux"
